odoo/addons/kubectl_import/LICENSE
odoo/addons/kubectl_import/__init__.py
odoo/addons/kubectl_import/__manifest__.py
odoo/addons/kubectl_import/images/screen.png
odoo/addons/kubectl_import/models/__init__.py
odoo/addons/kubectl_import/models/ir_actions_client.py
odoo/addons/kubectl_import/models/kubectl_context.py
odoo/addons/kubectl_import/models/kubectl_namespace.py
odoo/addons/kubectl_import/static/description/icon.png
odoo/addons/kubectl_import/views/kubectl_context_views.xml
odoo/addons/kubectl_import/views/kubectl_namespace_views.xml
odoo_addon_kubectl_import-18.0.1.0.0.dist-info/METADATA
odoo_addon_kubectl_import-18.0.1.0.0.dist-info/WHEEL
odoo_addon_kubectl_import-18.0.1.0.0.dist-info/top_level.txt
odoo_addon_kubectl_import-18.0.1.0.0.dist-info/RECORD
